{"cameraMode":{"drawMode":0,"name":"Shaded","section":"Shading Mode"},"sceneLighting":false,"audioPlay":false,"sceneViewState":{"m_AlwaysRefresh":false,"showFog":true,"showSkybox":false,"showFlares":true,"showImageEffects":true,"showParticleSystems":true,"showVisualEffectGraphs":true,"m_FxEnabled":true},"in2DMode":false,"pivot":{"x":0.07532262802124024,"y":1.9231096506118775,"z":5.200667858123779},"rotation":{"x":0.05973350256681442,"y":0.6437651515007019,"z":-0.05051666870713234,"w":0.7612172961235046},"size":9.772393226623536,"orthographic":false}